pritunl_api/__init__.py
pritunl_api/utils/__init__.py
pritunl_api/utils/keygen.py
pritunl_api/utils/query.py
pritunl_api_cli/__init__.py
pritunl_api_cli/commands/__init__.py
pritunl_api_cli/commands/api.py
pritunl_api_cli/commands/user.py
pritunl_api_cli/core/__init__.py
pritunl_api_cli/core/api.py
pritunl_api_cli/core/user.py
pritunl_api-1.1.12.dist-info/LICENSE
pritunl_api-1.1.12.dist-info/METADATA
pritunl_api-1.1.12.dist-info/WHEEL
pritunl_api-1.1.12.dist-info/entry_points.txt
pritunl_api-1.1.12.dist-info/RECORD
