Metadata-Version: 2.1
Name: pritunl-api
Version: 1.1.12
Summary: Pritunl API Client for Python
License: MIT
Author: Nathaniel Varona
Author-email: nathaniel.varona+pypi@gmail.com
Requires-Python: >=3.8,<4.0
Classifier: Development Status :: 4 - Beta
Classifier: Environment :: Console
Classifier: Environment :: Plugins
Classifier: Intended Audience :: Developers
Classifier: License :: OSI Approved :: MIT License
Classifier: Operating System :: MacOS :: MacOS X
Classifier: Operating System :: Microsoft :: Windows
Classifier: Operating System :: POSIX :: Linux
Classifier: Programming Language :: Python :: 3
Classifier: Programming Language :: Python :: 3.8
Classifier: Programming Language :: Python :: 3.9
Classifier: Programming Language :: Python :: 3.10
Classifier: Programming Language :: Python :: 3.11
Classifier: Programming Language :: Python :: 3.12
Classifier: Programming Language :: Python :: 3 :: Only
Classifier: Topic :: Software Development :: Libraries :: Python Modules
Classifier: Topic :: System :: Networking
Classifier: Topic :: System :: Systems Administration
Provides-Extra: cli
Provides-Extra: repl
Requires-Dist: click (==8.1.3) ; extra == "cli"
Requires-Dist: ipython (==8.11.0) ; extra == "repl"
Requires-Dist: ptpython (==3.0.23) ; extra == "repl"
Requires-Dist: requests (==2.31.0)
Requires-Dist: rich (==13.3.2) ; extra == "cli"
Project-URL: Downloads, https://github.com/nathanielvarona/pritunl-api-python
Project-URL: Documentation, https://github.com/nathanielvarona/pritunl-api-python
Project-URL: Homepage, https://github.com/nathanielvarona/pritunl-api-python
Project-URL: Source, https://github.com/nathanielvarona/pritunl-api-python
Project-URL: Tracker, https://github.com/nathanielvarona/pritunl-api-python
